[
  {
    "Id": "1213731",
    "ThreadId": "534841",
    "Html": "Hi Mark, et al.,\r<br />\nAs always, thanks for your fine library and hard work.\r<br />\n<br />\nMoving up to NAudio 1.7 now.\r<br />\n<br />\nI include these 2 assemblies with my app but rebuild them because my app requires signed assemblies (which is easy enough).\r<br />\n<br />\nNAudio.WindowsMediaFormat.dll\r<br />\nNAudio\\NAudio.dll\r<br />\n<br />\nQUESTION\r<br />\nIs there any problem with resetting the target .Net Framework to 4.0 Client Profile?\r<br />\n<br />\nThese two dlls build successfully with that framework level. Just wondering if there are any hidden runtime gotchas that I won't find  out about til later.<br />\n",
    "PostedDate": "2014-02-24T07:08:12.7-08:00",
    "UserRole": null,
    "MarkedAsAnswerDate": null
  },
  {
    "Id": "1213733",
    "ThreadId": "534841",
    "Html": "I don't think that should be an issue, but I haven't actually tried it<br />\n",
    "PostedDate": "2014-02-24T07:10:17.8-08:00",
    "UserRole": null,
    "MarkedAsAnswerDate": null
  },
  {
    "Id": "1213735",
    "ThreadId": "534841",
    "Html": "Thanks for the quick reply Mark. I'll do some testing and report back on results (success or not).<br />\n",
    "PostedDate": "2014-02-24T07:13:35.75-08:00",
    "UserRole": null,
    "MarkedAsAnswerDate": null
  },
  {
    "Id": "1215367",
    "ThreadId": "534841",
    "Html": "Just to report back, these 2 dlls rebuilt to .Net 4.0 Client Profile work fine. If I hit any bugs later during testing, I'll let post back here. But so far so good.  \r<br />\n",
    "PostedDate": "2014-02-26T15:43:19.62-08:00",
    "UserRole": null,
    "MarkedAsAnswerDate": null
  }
]